README.md
setup.py
prismic/__init__.py
prismic/api.py
prismic/cache.py
prismic/connection.py
prismic/exceptions.py
prismic/experiments.py
prismic/fragments.py
prismic/predicates.py
prismic/utils.py
prismic_httpx.egg-info/PKG-INFO
prismic_httpx.egg-info/SOURCES.txt
prismic_httpx.egg-info/dependency_links.txt
prismic_httpx.egg-info/requires.txt
prismic_httpx.egg-info/top_level.txt
tests/__init__.py
tests/test_connection.py
tests/test_doc.py
tests/test_experiments.py
tests/test_prismic.py
tests/test_prismic_fixtures.py