Metadata-Version: 2.1
Name: prismic-httpx
Version: 0.0.1
Summary: Asyncio fork of the Python client for prismic.io
Home-page: https://github.com/remidebette/prismic-httpx
Author: Rémi DEBETTE
Author-email: remi.debette@gmail.com
License: Apache 2
Platform: UNKNOWN
Classifier: Development Status :: 4 - Beta
Classifier: Operating System :: OS Independent
Classifier: Intended Audience :: Developers
Classifier: Environment :: Web Environment
Classifier: Framework :: AsyncIO
Classifier: Programming Language :: Python :: 3.6
Requires-Python: >=3.6
